niftypet/__init__.py
niftypet/ml/__init__.py
niftypet/ml/_dist_ver.py
niftypet/ml/layers.py
niftypet/ml/models.py
niftyml-1.0.0.dist-info/LICENCE
niftyml-1.0.0.dist-info/METADATA
niftyml-1.0.0.dist-info/WHEEL
niftyml-1.0.0.dist-info/top_level.txt
niftyml-1.0.0.dist-info/RECORD
